prequest/__init__.py
prequest/prequest.py
prequest-1.0.0.dist-info/DESCRIPTION.rst
prequest-1.0.0.dist-info/METADATA
prequest-1.0.0.dist-info/RECORD
prequest-1.0.0.dist-info/WHEEL
prequest-1.0.0.dist-info/metadata.json
prequest-1.0.0.dist-info/top_level.txt
